{"pii": "S0306437921001563", "abstracts": {"#name": "abstracts", "$": {"xmlns:ce": true, "xmlns:dm": true, "xmlns:sb": true}, "$$": [{"#name": "abstract", "$": {"class": "author", "view": "all", "id": "d1e772"}, "$$": [{"#name": "section-title", "$": {"id": "d1e773"}, "_": "Abstract"}, {"#name": "abstract-sec", "$": {"view": "all", "id": "d1e775"}, "$$": [{"#name": "simple-para", "$": {"view": "all", "id": "d1e776"}, "_": "The EU-funded project Lynx focuses on the creation of a knowledge graph for the legal domain (Legal Knowledge Graph, LKG) and its use for the semantic processing, analysis and enrichment of documents from the legal domain. This article describes the use cases covered in the project, the entire developed platform and the semantic analysis services that operate on the documents."}]}]}, {"#name": "abstract", "$": {"class": "author-highlights", "view": "all", "id": "d1e778"}, "$$": [{"#name": "section-title", "$": {"id": "d1e779"}, "_": "Highlights"}, {"#name": "abstract-sec", "$": {"view": "all", "id": "d1e781"}, "$$": [{"#name": "simple-para", "$": {"view": "all", "id": "d1e782"}, "$$": [{"#name": "list", "$": {"id": "d1e784"}, "$$": [{"#name": "list-item", "$": {"id": "d1e785"}, "$$": [{"#name": "label", "_": "\u2022"}, {"#name": "para", "$": {"view": "all", "id": "d1e788"}, "_": "The EU project Lynx has developed a Knowledge Graph for the legal domain (LKG)."}]}, {"#name": "list-item", "$": {"id": "d1e790"}, "$$": [{"#name": "label", "_": "\u2022"}, {"#name": "para", "$": {"view": "all", "id": "d1e793"}, "_": "The LKG interlinks a large number of documents through linguistic and semantic information."}]}, {"#name": "list-item", "$": {"id": "d1e795"}, "$$": [{"#name": "label", "_": "\u2022"}, {"#name": "para", "$": {"view": "all", "id": "d1e798"}, "_": "The Lynx technology platform includes a large number of semantic processing services."}]}, {"#name": "list-item", "$": {"id": "d1e800"}, "$$": [{"#name": "label", "_": "\u2022"}, {"#name": "para", "$": {"view": "all", "id": "d1e803"}, "_": "Multilingual services can be flexibly combined into complex tasks by a workflow manager."}]}, {"#name": "list-item", "$": {"id": "d1e805"}, "$$": [{"#name": "label", "_": "\u2022"}, {"#name": "para", "$": {"view": "all", "id": "d1e808"}, "_": "The three use cases benefit from the flexible Lynx platform and the multilingual LKG."}]}]}]}]}]}]}}