{"pii": "S2589004222007854", "abstracts": {"#name": "abstracts", "$": {"xmlns:ce": true, "xmlns:dm": true, "xmlns:sb": true}, "$$": [{"#name": "attachments", "$$": [{"#name": "attachment", "$": {"xmlns:xocs": true}, "$$": [{"#name": "attachment-eid", "_": "1-s2.0-S2589004222007854-fx1.jpg"}, {"#name": "ucs-locator", "_": "https://s3-eu-west-1.amazonaws.com/prod-ucs-content-store-eu-west/content/pii:S2589004222007854/fx1/DOWNSAMPLED/image/jpeg/37c83a83120f1a1401cc7705570187e5/fx1.jpg"}, {"#name": "file-basename", "_": "fx1"}, {"#name": "abstract-attachment", "_": "true"}, {"#name": "filename", "_": "fx1.jpg"}, {"#name": "extension", "_": "jpg"}, {"#name": "filesize", "_": "45645"}, {"#name": "pixel-height", "_": "375"}, {"#name": "pixel-width", "_": "375"}, {"#name": "attachment-type", "_": "IMAGE-DOWNSAMPLED"}]}, {"#name": "attachment", "$": {"xmlns:xocs": true}, "$$": [{"#name": "attachment-eid", "_": "1-s2.0-S2589004222007854-fx1.sml"}, {"#name": "ucs-locator", "_": "https://s3-eu-west-1.amazonaws.com/prod-ucs-content-store-eu-west/content/pii:S2589004222007854/fx1/HIGHRES/image/gif/d3cb48d29018cfc639234beff1bbaaa9/fx1.sml"}, {"#name": "file-basename", "_": "fx1"}, {"#name": "abstract-attachment", "_": "true"}, {"#name": "filename", "_": "fx1.sml"}, {"#name": "extension", "_": "sml"}, {"#name": "filesize", "_": "9529"}, {"#name": "pixel-height", "_": "164"}, {"#name": "pixel-width", "_": "164"}, {"#name": "attachment-type", "_": "IMAGE-THUMBNAIL"}]}, {"#name": "attachment", "$": {"xmlns:xocs": true}, "$$": [{"#name": "attachment-eid", "_": "1-s2.0-S2589004222007854-fx1_lrg.jpg"}, {"#name": "ucs-locator", "_": "https://s3-eu-west-1.amazonaws.com/prod-ucs-content-store-eu-west/content/pii:S2589004222007854/HIGHRES/image/jpeg/c1c0c3c5a649c3f912bf79b45ae3c3c2/fx1_lrg.jpg"}, {"#name": "file-basename", "_": "fx1"}, {"#name": "abstract-attachment", "_": "true"}, {"#name": "filename", "_": "fx1_lrg.jpg"}, {"#name": "extension", "_": "jpg"}, {"#name": "filesize", "_": "183881"}, {"#name": "pixel-height", "_": "996"}, {"#name": "pixel-width", "_": "996"}, {"#name": "attachment-type", "_": "IMAGE-HIGH-RES"}]}]}, {"#name": "abstract", "$": {"id": "abs0010", "view": "all", "class": "author"}, "$$": [{"#name": "section-title", "$": {"id": "sectitle0010"}, "_": "Summary"}, {"#name": "abstract-sec", "$": {"id": "abssec0010", "view": "all"}, "$$": [{"#name": "simple-para", "$": {"id": "abspara0010", "view": "all"}, "$$": [{"#name": "__text__", "_": "In the apex-directed RAB11 exocytic pathway of "}, {"#name": "italic", "_": "Aspergillus nidulans"}, {"#name": "__text__", "_": ", kinesin-1/KinA conveys secretory vesicles (SVs) to the hyphal tip, where they are transferred to the type V myosin MyoE. MyoE concentrates SVs at an apical store located underneath the PM resembling the presynaptic active zone. A rod-shaped RAB11 effector, UDS1, and the intrinsically disordered and coiled-coil HMSV associate with MyoE in a stable HUM (HMSV-UDS1-MyoE) complex recruited by RAB11 to SVs through an interaction network involving RAB11 and HUM components, with the MyoE globular tail domain (GTD) binding both HMSV and RAB11-GTP and RAB11-GTP binding both the MyoE-GTD and UDS1. UDS1 bridges RAB11-GTP to HMSV, an avid interactor of the MyoE-GTD. The interaction between the UDS1-HMSV sub-complex and RAB11-GTP can be reconstituted "}, {"#name": "italic", "_": "in\u00a0vitro"}, {"#name": "__text__", "_": ". Ablating UDS1 or HMSV impairs actomyosin-mediated transport of SVs to the apex, resulting in spreading of RAB11 SVs across the apical dome as KinA/microtubule-dependent transport gains prominence."}]}]}]}, {"#name": "abstract", "$": {"class": "graphical", "id": "abs0015", "view": "all"}, "$$": [{"#name": "section-title", "$": {"id": "sectitle0015"}, "_": "Graphical abstract"}, {"#name": "abstract-sec", "$": {"id": "abssec0015", "view": "all"}, "$$": [{"#name": "simple-para", "$": {"id": "abspara0015", "view": "all"}, "$$": [{"#name": "display", "$$": [{"#name": "figure", "$": {"id": "undfig1"}, "$$": [{"#name": "link", "$": {"xmlns:xlink": true, "locator": "fx1", "type": "simple", "href": "pii:S2589004222007854/fx1", "id": "aep-link-id8"}}]}]}]}]}]}, {"#name": "abstract", "$": {"class": "author-highlights", "id": "abs0020", "view": "all"}, "$$": [{"#name": "section-title", "$": {"id": "sectitle0020"}, "_": "Highlights"}, {"#name": "abstract-sec", "$": {"id": "abssec0020", "view": "all"}, "$$": [{"#name": "simple-para", "$": {"id": "abspara0020", "view": "all"}, "$$": [{"#name": "list", "$": {"id": "ulist0010"}, "$$": [{"#name": "list-item", "$": {"id": "u0010"}, "$$": [{"#name": "label", "_": "\u2022"}, {"#name": "para", "$": {"id": "p0010", "view": "all"}, "_": "An apical exocytic organelle acting as vesicle supply center drives hyphal growth"}]}, {"#name": "list-item", "$": {"id": "u0015"}, "$$": [{"#name": "label", "_": "\u2022"}, {"#name": "para", "$": {"id": "p0015", "view": "all"}, "_": "Myosin V delivers RAB11 vesicles to this apical organelle, focusing exocytosis"}]}, {"#name": "list-item", "$": {"id": "u0020"}, "$$": [{"#name": "label", "_": "\u2022"}, {"#name": "para", "$": {"id": "p0020", "view": "all"}, "_": "RAB11 is the key organizer of the HUM complex recruiting myosin V to vesicles"}]}, {"#name": "list-item", "$": {"id": "u0025"}, "$$": [{"#name": "label", "_": "\u2022"}, {"#name": "para", "$": {"id": "p0025", "view": "all"}, "_": "Impairing HUM shifts myosin traffic to microtubules, defocusing secretory vesicles"}]}]}]}]}]}, {"#name": "abstract", "$": {"class": "teaser", "id": "abs0025", "view": "all"}, "$$": [{"#name": "abstract-sec", "$": {"id": "abssec0025", "view": "all"}, "$$": [{"#name": "simple-para", "$": {"id": "abspara0025", "view": "all"}, "_": "Biological sciences; Biochemistry; Molecular biology"}]}]}]}}